qlytix_package/__init__.py
qlytix_package/datasource.py
qlytix_package/masterdata.py
qlytix_package/user.py
qlytix_package-4.0.dist-info/METADATA
qlytix_package-4.0.dist-info/WHEEL
qlytix_package-4.0.dist-info/top_level.txt
qlytix_package-4.0.dist-info/RECORD
