Metadata-Version: 2.1
Name: qlytix-package
Version: 4.0
Summary: User and Auth Data
Author: Kranthi
Author-email: kk@gmail.com
License: MIT
